[
  {
    "cpu_usada": 42,
    "timestamp": "2025-03-14T23:31:48.832862464+00:00"
  },
  {
    "cpu_usada": 20,
    "timestamp": "2025-03-14T23:31:58.840237854+00:00"
  },
  {
    "cpu_usada": 40,
    "timestamp": "2025-03-14T23:32:08.852109132+00:00"
  },
  {
    "cpu_usada": 87,
    "timestamp": "2025-03-14T23:32:18.863185130+00:00"
  },
  {
    "cpu_usada": 87,
    "timestamp": "2025-03-14T23:32:39.565022564+00:00"
  },
  {
    "cpu_usada": 75,
    "timestamp": "2025-03-14T23:32:54.804797324+00:00"
  },
  {
    "cpu_usada": 59,
    "timestamp": "2025-03-14T23:33:04.858784738+00:00"
  },
  {
    "cpu_usada": 52,
    "timestamp": "2025-03-14T23:33:26.127030561+00:00"
  },
  {
    "cpu_usada": 78,
    "timestamp": "2025-03-14T23:34:02.407141614+00:00"
  },
  {
    "cpu_usada": 79,
    "timestamp": "2025-03-14T23:34:47.981463997+00:00"
  },
  {
    "cpu_usada": 81,
    "timestamp": "2025-03-14T23:35:19.692922790+00:00"
  },
  {
    "cpu_usada": 92,
    "timestamp": "2025-03-14T23:35:43.834257981+00:00"
  },
  {
    "cpu_usada": 76,
    "timestamp": "2025-03-14T23:36:30.236498639+00:00"
  },
  {
    "cpu_usada": 57,
    "timestamp": "2025-03-14T23:36:49.300330034+00:00"
  },
  {
    "cpu_usada": 82,
    "timestamp": "2025-03-14T23:37:13.177898264+00:00"
  },
  {
    "cpu_usada": 57,
    "timestamp": "2025-03-14T23:38:10.621956525+00:00"
  },
  {
    "cpu_usada": 89,
    "timestamp": "2025-03-14T23:39:09.904680951+00:00"
  },
  {
    "cpu_usada": 68,
    "timestamp": "2025-03-14T23:40:30.611599661+00:00"
  },
  {
    "cpu_usada": 72,
    "timestamp": "2025-03-14T23:41:41.256866853+00:00"
  },
  {
    "cpu_usada": 68,
    "timestamp": "2025-03-14T23:43:22.453662008+00:00"
  },
  {
    "cpu_usada": 67,
    "timestamp": "2025-03-14T23:44:43.856037091+00:00"
  },
  {
    "cpu_usada": 71,
    "timestamp": "2025-03-14T23:46:24.202391355+00:00"
  },
  {
    "cpu_usada": 72,
    "timestamp": "2025-03-14T23:48:09.001946601+00:00"
  },
  {
    "cpu_usada": 71,
    "timestamp": "2025-03-14T23:50:14.930816504+00:00"
  },
  {
    "cpu_usada": 69,
    "timestamp": "2025-03-14T23:53:00.423244561+00:00"
  },
  {
    "cpu_usada": 57,
    "timestamp": "2025-03-14T23:56:22.995786580+00:00"
  },
  {
    "cpu_usada": 69,
    "timestamp": "2025-03-14T23:59:31.612646997+00:00"
  },
  {
    "cpu_usada": 53,
    "timestamp": "2025-03-15T00:03:58.886189572+00:00"
  },
  {
    "cpu_usada": 65,
    "timestamp": "2025-03-15T00:09:22.218950993+00:00"
  },
  {
    "cpu_usada": 71,
    "timestamp": "2025-03-15T00:15:34.014847860+00:00"
  },
  {
    "cpu_usada": 70,
    "timestamp": "2025-03-15T00:23:09.776915434+00:00"
  },
  {
    "cpu_usada": 83,
    "timestamp": "2025-03-15T00:29:36.809864805+00:00"
  },
  {
    "cpu_usada": 84,
    "timestamp": "2025-03-15T00:38:14.312719838+00:00"
  },
  {
    "cpu_usada": 0,
    "timestamp": "2025-03-15T13:37:03.866768322+00:00"
  },
  {
    "cpu_usada": 19,
    "timestamp": "2025-03-15T13:37:13.908739784+00:00"
  },
  {
    "cpu_usada": 28,
    "timestamp": "2025-03-15T13:37:23.922943486+00:00"
  },
  {
    "cpu_usada": 13,
    "timestamp": "2025-03-15T13:37:33.938157991+00:00"
  },
  {
    "cpu_usada": 33,
    "timestamp": "2025-03-15T13:37:43.951645725+00:00"
  },
  {
    "cpu_usada": 21,
    "timestamp": "2025-03-15T13:37:53.966941896+00:00"
  },
  {
    "cpu_usada": 14,
    "timestamp": "2025-03-15T13:38:03.982799432+00:00"
  },
  {
    "cpu_usada": 38,
    "timestamp": "2025-03-15T13:38:13.998347418+00:00"
  },
  {
    "cpu_usada": 85,
    "timestamp": "2025-03-15T13:38:24.007301514+00:00"
  },
  {
    "cpu_usada": 90,
    "timestamp": "2025-03-15T13:38:34.020827358+00:00"
  },
  {
    "cpu_usada": 56,
    "timestamp": "2025-03-15T13:38:57.902205527+00:00"
  },
  {
    "cpu_usada": 68,
    "timestamp": "2025-03-15T13:39:19.579393478+00:00"
  },
  {
    "cpu_usada": 68,
    "timestamp": "2025-03-15T13:39:59.282034070+00:00"
  },
  {
    "cpu_usada": 83,
    "timestamp": "2025-03-15T13:40:46.602269297+00:00"
  },
  {
    "cpu_usada": 93,
    "timestamp": "2025-03-15T13:42:09.203758290+00:00"
  },
  {
    "cpu_usada": 82,
    "timestamp": "2025-03-15T13:43:20.627029236+00:00"
  },
  {
    "cpu_usada": 70,
    "timestamp": "2025-03-15T13:45:03.875425355+00:00"
  },
  {
    "cpu_usada": 73,
    "timestamp": "2025-03-15T13:47:07.508736218+00:00"
  },
  {
    "cpu_usada": 67,
    "timestamp": "2025-03-15T13:50:18.831044473+00:00"
  },
  {
    "cpu_usada": 66,
    "timestamp": "2025-03-15T13:54:17.736566674+00:00"
  },
  {
    "cpu_usada": 71,
    "timestamp": "2025-03-15T13:58:55.552864871+00:00"
  },
  {
    "cpu_usada": 61,
    "timestamp": "2025-03-15T14:00:38.991578822+00:00"
  },
  {
    "cpu_usada": 59,
    "timestamp": "2025-03-15T14:07:12.730235486+00:00"
  },
  {
    "cpu_usada": 0,
    "timestamp": "2025-03-15T14:21:42.404904433+00:00"
  },
  {
    "cpu_usada": 22,
    "timestamp": "2025-03-15T14:21:52.613819517+00:00"
  },
  {
    "cpu_usada": 26,
    "timestamp": "2025-03-15T14:22:02.630948336+00:00"
  },
  {
    "cpu_usada": 67,
    "timestamp": "2025-03-15T14:22:12.831146771+00:00"
  },
  {
    "cpu_usada": 91,
    "timestamp": "2025-03-15T14:22:33.059878129+00:00"
  },
  {
    "cpu_usada": 67,
    "timestamp": "2025-03-15T14:23:07.677811758+00:00"
  },
  {
    "cpu_usada": 32,
    "timestamp": "2025-03-15T14:23:40.822786535+00:00"
  },
  {
    "cpu_usada": 45,
    "timestamp": "2025-03-15T14:24:36.605140257+00:00"
  },
  {
    "cpu_usada": 35,
    "timestamp": "2025-03-15T14:25:42.820432552+00:00"
  }
]